t_pomo/t_pomo.py
t_pomo-0.6.0.dist-info/LICENSE
t_pomo-0.6.0.dist-info/METADATA
t_pomo-0.6.0.dist-info/WHEEL
t_pomo-0.6.0.dist-info/entry_points.txt
t_pomo-0.6.0.dist-info/RECORD
