Metadata-Version: 2.3
Name: t-pomo
Version: 0.6.0
Summary: A simple Pomodoro timer with ASCII art display that runs on terminal.
License: MIT
Author: uuboyscy
Author-email: uuboyscy@uuboyscy.dev
Requires-Python: >=3.9
Classifier: License :: OSI Approved :: MIT License
Classifier: Programming Language :: Python :: 3
Classifier: Programming Language :: Python :: 3.9
Classifier: Programming Language :: Python :: 3.10
Classifier: Programming Language :: Python :: 3.11
Classifier: Programming Language :: Python :: 3.12
Classifier: Programming Language :: Python :: 3.13
Requires-Dist: art (>=6.4,<7.0)
Requires-Dist: inspirational-quotes (>=0.0.16,<0.0.17)
Project-URL: Homepage, https://github.com/uuboyscy/t-pomo
Project-URL: Issues, https://github.com/uuboyscy/t-pomo/issues
